{"expireTime":9007200873369334000,"key":"612c2e1aae22dfa0e5bdeaed10300aa8","val":{"name":"IMAGE_PROCESSING","inputPaths":["C:/Users/CHLO/qulo-portfolio/qulo-portfolio-gatsby/content/blog/fur/charles-deluvio-540415-unsplash.jpg"],"outputDir":"C:/Users/CHLO/qulo-portfolio/qulo-portfolio-gatsby/public/static/a1ebbea943f183782485fb7212e283bb","args":{"isLazy":false,"operations":[{"outputPath":"2e524\\charles-deluvio-540415-unsplash.jpg","args":{"width":340,"toFormat":"jpg","quality":75}},{"outputPath":"d330d\\charles-deluvio-540415-unsplash.jpg","args":{"width":680,"toFormat":"jpg","quality":75}},{"outputPath":"6c26c\\charles-deluvio-540415-unsplash.jpg","args":{"width":1360,"toFormat":"jpg","quality":75}},{"outputPath":"cbe2c\\charles-deluvio-540415-unsplash.jpg","args":{"width":2000,"toFormat":"jpg","quality":75}}],"pluginOptions":{"base64Width":20,"forceBase64Format":"","useMozJpeg":false,"stripMetadata":true,"lazyImageGeneration":true,"defaultQuality":50,"failOnError":true,"plugins":[]}}}}